{
  "name": "Flávio",
  "photo": "https://avatars.githubusercontent.com/u/12720556?v=4",
  "job": "Junior Front-end Developer",
  "location": "Brasília - DF",
  "phone": "61 99202-6954",
  "email": "flavio.cmb@gmail.com",
  "skills": {
    "hardSkills": [
      {
        "name": "HTML",
        "src": "https://raw.githubusercontent.com/flaviocmb/portfolio/main/assets/data/img/html.svg"
      },
      {
        "name": "CSS",
        "src": "https://raw.githubusercontent.com/flaviocmb/portfolio/main/assets/data/img/css.svg"
      },
      {
        "name": "JavaScript",
        "src": "https://raw.githubusercontent.com/flaviocmb/portfolio/main/assets/data/img/javascript.svg"
      }
    ],
    "softSkills": [
      "Organização",
      "Consistência",
      "Perfil Evolutivo",
      "Trabalho em equipe",
      "Facilidade de comunicação",
      "Comprometimento com resultados"
    ]
  },
  "languages": [
    "Português",
    "Inglês",
    "Alemão"
  ],
  "portfolio": [
    {
      "name": "E-commerce de livros front-end com HTML, CSS e Javascript",
      "url": "https://www.google.com.br",
      "github": true
    }
  ],
  "professionalExperience": [
    {
      "name": "Técnico de Suporte / iPlace",
      "period": "02/2011 – 05/2015",
      "description": "Lorem ipsum dolor sit amet consectetur adipisicing elit. Quos dolor officiis dicta repellendus eligendi molestiae natus soluta non ratione maiores."
    }
  ]
}
